ganzua/__init__.py
ganzua/_cli_help.py
ganzua/_constraints.py
ganzua/_diff.py
ganzua/_lockfile.py
ganzua/_markdown.py
ganzua/_pretty_specifier_set.py
ganzua/_pyproject.py
ganzua/_toml.py
ganzua/_utils.py
ganzua/cli.py
ganzua/py.typed
ganzua-0.2.0.dist-info/METADATA
ganzua-0.2.0.dist-info/WHEEL
ganzua-0.2.0.dist-info/entry_points.txt
ganzua-0.2.0.dist-info/licenses/LICENSE.txt
ganzua-0.2.0.dist-info/RECORD
