Metadata-Version: 2.4
Name: ganzua
Version: 0.2.0
Summary: extract dependency information from lockfiles
Project-URL: Repository, https://github.com/latk/ganzua
Author-email: Lukas Atkinson <opensource@LukasAtkinson.de>
License-Expression: Apache-2.0
License-File: LICENSE.txt
Keywords: dependabot,dependency,packaging,poetry,requirements,uv
Classifier: Intended Audience :: Developers
Classifier: License :: OSI Approved :: Apache Software License
Requires-Python: >=3.12
Requires-Dist: click>=8.2.1
Requires-Dist: packaging>=25.0
Requires-Dist: pydantic>=2.11.7
Requires-Dist: rich>=14.1.0
Requires-Dist: tomlkit>=0.13.3
